MANIFEST.in
README.md
setup.cfg
setup.py
scripts/fml
scripts/ingestIt
scripts/mailIt
scripts/mrFilmOut
scripts/noteBao
scripts/reports
scripts/vfxConfigManager
scripts/vfxTray
tests/__init__.py
tests/test_import.py
vfxClientToolkit/__init__.py
vfxClientToolkit/_version.py
vfxClientToolkit/constants.py
vfxClientToolkit.egg-info/PKG-INFO
vfxClientToolkit.egg-info/SOURCES.txt
vfxClientToolkit.egg-info/dependency_links.txt
vfxClientToolkit.egg-info/requires.txt
vfxClientToolkit.egg-info/top_level.txt
vfxClientToolkit/api/__init__.py
vfxClientToolkit/api/config.py
vfxClientToolkit/api/dropbox.py
vfxClientToolkit/api/entities.py
vfxClientToolkit/api/logger.py
vfxClientToolkit/api/sg.py
vfxClientToolkit/configs/__init__.py
vfxClientToolkit/configs/vfxCTK_config_email.json
vfxClientToolkit/configs/vfxCTK_config_filesystem.json
vfxClientToolkit/configs/vfxCTK_config_fml.json
vfxClientToolkit/configs/vfxCTK_config_ingestIt.json
vfxClientToolkit/configs/vfxCTK_config_mailIt.json
vfxClientToolkit/configs/vfxCTK_config_mrFilmOut.json
vfxClientToolkit/configs/vfxCTK_config_push.json
vfxClientToolkit/configs/vfxCTK_config_reports.json
vfxClientToolkit/configs/vfxCTK_config_shotgun.json
vfxClientToolkit/configs/utils/__init__.py
vfxClientToolkit/configs/utils/emailUtil.py
vfxClientToolkit/configs/utils/filesystem.py
vfxClientToolkit/configs/utils/fml.py
vfxClientToolkit/configs/utils/ingestIt.py
vfxClientToolkit/configs/utils/mailIt.py
vfxClientToolkit/configs/utils/push.py
vfxClientToolkit/configs/utils/shotgun.py
vfxClientToolkit/html_templates/template.html
vfxClientToolkit/icons/__init__.py
vfxClientToolkit/icons/arrow_left.png
vfxClientToolkit/icons/arrow_right.png
vfxClientToolkit/icons/cat_icon.png
vfxClientToolkit/icons/checked_icon.png
vfxClientToolkit/icons/help_icon.png
vfxClientToolkit/icons/jake_icon.png
vfxClientToolkit/icons/minus_icon.png
vfxClientToolkit/icons/moose_icon.png
vfxClientToolkit/icons/package_icon.png
vfxClientToolkit/icons/plus_icon.png
vfxClientToolkit/icons/red_cross.png
vfxClientToolkit/icons/refresh_icon.png
vfxClientToolkit/ui/__init__.py
vfxClientToolkit/ui/about.py
vfxClientToolkit/ui/combo_checkbox.py
vfxClientToolkit/ui/utils.py
