Metadata-Version: 1.1
Name: vfxClientToolkit
Version: 0.0.2
Summary: Utilities for processing versions and notes for VFX client side.
Home-page: https://github.com/debug/vfxClientToolkit
Author: Dom Drane
Author-email: dom@reality-debug.co.uk
License: MIT
Platform: UNKNOWN
Classifier: License :: OSI Approved :: MIT License
